wellbeing_calculator/__init__.py
wellbeing_calculator/calculator.py
wellbeing_calculator-0.5.dist-info/METADATA
wellbeing_calculator-0.5.dist-info/WHEEL
wellbeing_calculator-0.5.dist-info/entry_points.txt
wellbeing_calculator-0.5.dist-info/top_level.txt
wellbeing_calculator-0.5.dist-info/RECORD
