Metadata-Version: 2.1
Name: wellbeing-calculator
Version: 0.5
Summary: A tool to evaluate the impact of social media usage on personal wellbeing and lifestyle habits
Home-page: https://github.com/yourusername/wellbeing_calculator
Author: Your Name
Author-email: your-email@example.com
License: MIT
Platform: UNKNOWN
Classifier: Programming Language :: Python :: 3
Classifier: License :: OSI Approved :: MIT License
Classifier: Operating System :: OS Independent
Requires-Python: >=3.6
Requires-Dist: pandas
